jupyter_myst_build_proxy/__init__.py
jupyter_myst_build_proxy/building.html
jupyter_myst_build_proxy/directory_browser.html
jupyter_myst_build_proxy/logo-square.svg
jupyter_myst_build_proxy/remixContextMod.html
jupyter_myst_build_proxy/static_server.py
jupyter_myst_build_proxy-0.5.0.data/data/share/jupyter/labextensions/jupyter-myst-build-proxy/package.json
jupyter_myst_build_proxy-0.5.0.data/data/share/jupyter/labextensions/jupyter-myst-build-proxy/static/509.7fdc63b1a2f6e9667f63.js
jupyter_myst_build_proxy-0.5.0.data/data/share/jupyter/labextensions/jupyter-myst-build-proxy/static/remoteEntry.eb1c4dfc259d7fcc977e.js
jupyter_myst_build_proxy-0.5.0.data/data/share/jupyter/labextensions/jupyter-myst-build-proxy/static/style.js
jupyter_myst_build_proxy-0.5.0.data/data/share/jupyter/labextensions/jupyter-myst-build-proxy/static/third-party-licenses.json
jupyter_myst_build_proxy-0.5.0.dist-info/METADATA
jupyter_myst_build_proxy-0.5.0.dist-info/WHEEL
jupyter_myst_build_proxy-0.5.0.dist-info/entry_points.txt
jupyter_myst_build_proxy-0.5.0.dist-info/licenses/LICENSE
jupyter_myst_build_proxy-0.5.0.dist-info/RECORD
