Metadata-Version: 2.4
Name: jupyter-myst-build-proxy
Version: 0.5.0
Summary: Jupyter extension to proxy MyST build server
Project-URL: Homepage, https://github.com/ryanlovett/jupyter-myst-build-proxy
Project-URL: Repository, https://github.com/ryanlovett/jupyter-myst-build-proxy
Project-URL: Issues, https://github.com/ryanlovett/jupyter-myst-build-proxy/issues
Author: Ryan Lovett
License: BSD-3-Clause
License-File: LICENSE
Keywords: Jupyter
Classifier: Framework :: Jupyter
Classifier: License :: OSI Approved :: BSD License
Classifier: Programming Language :: Python :: 3
Requires-Python: >=3.8
Requires-Dist: jupyter-server-proxy>4.1.0
